marathon_acme/__init__.py
marathon_acme/acme_util.py
marathon_acme/cli.py
marathon_acme/clients.py
marathon_acme/marathon_util.py
marathon_acme/server.py
marathon_acme/service.py
marathon_acme/sse_protocol.py
marathon_acme/tests/__init__.py
marathon_acme/tests/fake_marathon.py
marathon_acme/tests/helpers.py
marathon_acme/tests/matchers.py
marathon_acme/tests/test_acme_util.py
marathon_acme/tests/test_cli.py
marathon_acme/tests/test_clients.py
marathon_acme/tests/test_fake_marathon.py
marathon_acme/tests/test_marathon_util.py
marathon_acme/tests/test_server.py
marathon_acme/tests/test_service.py
marathon_acme/tests/test_sse_protocol.py
marathon_acme/tests/test_test_helpers.py
marathon_acme/tests/test_test_matchers.py
marathon_acme-0.6.1.dist-info/METADATA
marathon_acme-0.6.1.dist-info/RECORD
marathon_acme-0.6.1.dist-info/WHEEL
marathon_acme-0.6.1.dist-info/entry_points.txt
marathon_acme-0.6.1.dist-info/top_level.txt
