Metadata-Version: 2.1
Name: marathon-acme
Version: 0.6.1
Summary: Automated management of Let's Encrypt certificates for apps running on Mesosphere Marathon
Home-page: https://github.com/praekeltfoundation/marathon-acme
Author: Jamie Hewland
Author-email: jamie@praekelt.org
License: MIT
Platform: UNKNOWN
Classifier: Development Status :: 4 - Beta
Classifier: Framework :: Twisted
Classifier: Intended Audience :: System Administrators
Classifier: License :: OSI Approved :: MIT License
Classifier: Natural Language :: English
Classifier: Programming Language :: Python :: 2
Classifier: Programming Language :: Python :: 2.7
Classifier: Programming Language :: Python :: 3
Classifier: Programming Language :: Python :: 3.4
Classifier: Programming Language :: Python :: 3.5
Classifier: Programming Language :: Python :: 3.6
Classifier: Programming Language :: Python :: Implementation :: CPython
Classifier: Programming Language :: Python :: Implementation :: PyPy
Provides-Extra: test
Provides-Extra: pep8test
Requires-Dist: acme (>=0.21.0)
Requires-Dist: cryptography
Requires-Dist: josepy
Requires-Dist: klein
Requires-Dist: requests
Requires-Dist: treq (>=17.3.1)
Requires-Dist: Twisted[tls]
Requires-Dist: txacme (>=0.9.2)
Requires-Dist: uritools (>=1.0.0)
Provides-Extra: pep8test
Requires-Dist: flake8; extra == 'pep8test'
Requires-Dist: flake8-import-order; extra == 'pep8test'
Provides-Extra: test
Requires-Dist: fixtures; extra == 'test'
Requires-Dist: pem (>=16.1.0); extra == 'test'
Requires-Dist: pytest (>=3.0.0); extra == 'test'
Requires-Dist: testtools; extra == 'test'
Requires-Dist: txfake (>=0.1.1); extra == 'test'
